LICENSE.txt
setup.py
code/__init__.py
ikm.egg-info/PKG-INFO
ikm.egg-info/SOURCES.txt
ikm.egg-info/dependency_links.txt
ikm.egg-info/top_level.txt